PyLuaLinker/__init__.py
PyLuaLinker/__main__.py
PyLuaLinker/build_data.py
PyLuaLinker/linker.py
PyLuaLinker/utils.py
PyLuaLinker/commands/__init__.py
PyLuaLinker/commands/build.py
PyLuaLinker/commands/new.py
PyLuaLinker/dependency_tree/__init__.py
PyLuaLinker/dependency_tree/node.py
PyLuaLinker/dependency_tree/tree.py
data/buildscript.json
pylualinker-0.1.0.dist-info/METADATA
pylualinker-0.1.0.dist-info/WHEEL
pylualinker-0.1.0.dist-info/entry_points.txt
pylualinker-0.1.0.dist-info/licenses/LICENSE
pylualinker-0.1.0.dist-info/RECORD
