Metadata-Version: 2.1
Name: PyLuaLinker
Version: 0.1.0
Summary: A command-line tool for linking Lua projects into a single file
Project-URL: Homepage, https://github.com/Ubus99/PyLuaLinker
Project-URL: Issues, https://github.com/Ubus99/PyLuaLinker/issues
Author: Ubus99
License-File: LICENSE
Keywords: LUA,linker,scrips
Classifier: License :: OSI Approved :: GNU General Public License v3 (GPLv3)
Classifier: Operating System :: OS Independent
Classifier: Programming Language :: Python :: 3
Requires-Python: >=3.8
